{
    // Consultez https://go.microsoft.com//fwlink//?linkid=834763 pour plus d'informations sur ce fichier.
    "configurations": [
      {
        "name": "x86-Debug",
        "generator": "Visual Studio 15 2017",
        "configurationType": "Debug",
        "buildRoot": "${projectDir}\\cmake-build-debug",
        "cmakeCommandArgs": "",
        "buildCommandArgs": "-m -v:minimal"
      },
      {
        "name": "x86-Release",
        "generator": "Visual Studio 15 2017",
        "configurationType": "Release",
        "buildRoot": "${projectDir}\\cmake-build-release",
        "cmakeCommandArgs": "",
        "buildCommandArgs": "-m -v:minimal"
      },
      {
        "name": "x64-Debug",
        "generator": "Visual Studio 15 2017 Win64",
        "configurationType": "Debug",
        "buildRoot": "${projectDir}\\cmake-build-debug",
        "cmakeCommandArgs": "-m 1",
        "buildCommandArgs": "-m:4 -v:m -nr:True"
      },
      {
        "name": "x64-Release",
        "generator": "Visual Studio 15 2017 Win64",
        "configurationType": "Release",
        "buildRoot": "${projectDir}\\cmake-build-release",
        "cmakeCommandArgs": "-m 1",
        "buildCommandArgs": "-m:4 -v:m -nr:True"
      }
    ]
}